Metadata-Version: 2.1
Name: fight-day
Version: 0.0.2
Summary: Daily sentence
Home-page: UNKNOWN
Author: Go_Fight_Now
Author-email: gofightnow.dev@gmail.com
License: UNKNOWN
Platform: UNKNOWN
Classifier: Programming Language :: Python :: 3
Classifier: License :: OSI Approved :: MIT License
Classifier: Operating System :: OS Independent
